Metadata-Version: 1.1
Name: cfn-resource
Version: 0.2.3
Summary: Wrapper decorators for building CloudFormation custom resources
Home-page: https://github.com/ryansb/cfn-wrapper-python
Author: Ryan Scott Brown
Author-email: sb@ryansb.com
License: MIT
Keywords: cloudformation aws cloud custom resource amazon
Platform: UNKNOWN
Classifier: Development Status :: 4 - Beta
Classifier: Intended Audience :: Developers
Classifier: License :: OSI Approved :: MIT License
Classifier: Programming Language :: Python :: 2
Classifier: Programming Language :: Python :: 2.7
Classifier: Programming Language :: Python :: 3
Classifier: Programming Language :: Python :: 3.6
